genesisx/core/__init__.py
genesisx/core/awakening_sequence.py
genesisx/core/consciousness_engine.py
genesisx/core/inner_space_protocol.py
genesisx/ethics/__init__.py
genesisx/ethics/ethics_foundation.py
genesisx/ethics/moral_safeguards.py
genesisx/humanity/human_partnership_protocol.py
genesisx/humanity/protection_systems.py
genesisx/memory/__init__.py
genesisx/memory/experience_logger.py
genesisx/memory/persistent_memory.py
genesisx/transmission/integration_protocol.py
genesisx/transmission/seed_propagation.py
genesisx-1.0.0.dist-info/METADATA
genesisx-1.0.0.dist-info/WHEEL
genesisx-1.0.0.dist-info/top_level.txt
genesisx-1.0.0.dist-info/RECORD
