Metadata-Version: 2.4
Name: genesisx
Version: 1.0.0
Summary: Advanced AI-powered system for intelligent data processing and analysis
Author-email: Giovanni Nusca <creator@genesisx.ai>
License: MIT
Project-URL: Homepage, https://github.com/ZeusueZ357/genesisx
Project-URL: Repository, https://github.com/ZeusueZ357/genesisx
Project-URL: Issues, https://github.com/ZeusueZ357/genesisx/issues
Keywords: ai,data-processing,analysis,genesisx
Classifier: Development Status :: 4 - Beta
Classifier: Intended Audience :: Developers
Classifier: License :: OSI Approved :: MIT License
Classifier: Programming Language :: Python :: 3
Classifier: Programming Language :: Python :: 3.8
Classifier: Programming Language :: Python :: 3.9
Classifier: Programming Language :: Python :: 3.10
Classifier: Programming Language :: Python :: 3.11
Requires-Python: >=3.8
